routerfy/__init__.py
routerfy/cli.py
routerfy/debug.py
routerfy/development/__init__.py
routerfy/development/fastapi.py
routerfy/examples/routes/hello_world/app.py
routerfy/examples/routes/hello_world/route.py
routerfy/exceptions/__init__.py
routerfy/exceptions/invalidations.py
routerfy/exceptions/not_found.py
routerfy/integrations/__init__.py
routerfy/integrations/routerfy_integration.py
routerfy/integrations/apigateway/__init__.py
routerfy/integrations/apigateway/lambda_integration_v1.py
routerfy/integrations/apigateway/lambda_integration_v2.py
routerfy/models/__init__.py
routerfy/models/base_model.py
routerfy/models/aws/__init__.py
routerfy/models/aws/aws_serverless_api_template.py
routerfy/models/aws/aws_serverless_function_template.py
routerfy/models/aws/aws_template.py
routerfy/network/__init__.py
routerfy/network/request.py
routerfy/network/response.py
routerfy/network/url.py
routerfy/routing/__init__.py
routerfy/routing/api_router.py
routerfy/routing/route.py
routerfy/types/__init__.py
routerfy/types/routerfy_config.py
routerfy/types/aws/__init__.py
routerfy/types/aws/aws_serverless_api.py
routerfy/types/aws/aws_serverless_function.py
routerfy/utils/__init__.py
routerfy/utils/config.py
routerfy/utils/format.py
routerfy/utils/net.py
routerfy/utils/yaml/__init__.py
routerfy/utils/yaml/dumper.py
routerfy/utils/yaml/find_in_map.py
routerfy/utils/yaml/loader.py
routerfy/utils/yaml/ref.py
routerfy/utils/yaml/sub.py
routerfy-1.0.0b1.dist-info/LICENSE
routerfy-1.0.0b1.dist-info/METADATA
routerfy-1.0.0b1.dist-info/WHEEL
routerfy-1.0.0b1.dist-info/entry_points.txt
routerfy-1.0.0b1.dist-info/top_level.txt
routerfy-1.0.0b1.dist-info/RECORD
