Metadata-Version: 2.1
Name: routerfy
Version: 1.0.0b1
Summary: O Routerfy tem uma sintaxe similar ao FastAPI. Feito para ser leve e de fácil uso para serviços AWS Serverless.
Home-page: https://github.pactual.net/bruno-s-junqueira/routerfy
Author: Bruno Junqueira & Mateus Brazil
Author-email: brunosdsj@gmail.com
License: MIT
Classifier: Programming Language :: Python :: 3.8
Classifier: Operating System :: OS Independent
Requires-Python: >=3.7
License-File: LICENSE
Provides-Extra: dev
Requires-Dist: click >=7.1.2 ; extra == 'dev'
Requires-Dist: fastapi ==0.108.0 ; extra == 'dev'
Requires-Dist: uvicorn ==0.25.0 ; extra == 'dev'
Requires-Dist: python-dotenv ; extra == 'dev'
Requires-Dist: pyyaml ; extra == 'dev'
